{
  "method": "m2",
  "config": "A",
  "seed": 2,
  "best_epoch": 280,
  "best_val": 0.8930893395582835,
  "metric": "ssim",
  "history": [
    {
      "epoch": 0,
      "val": 0.707934898074468
    },
    {
      "epoch": 10,
      "val": 0.8341810561498008
    },
    {
      "epoch": 20,
      "val": 0.8407407086054484
    },
    {
      "epoch": 30,
      "val": 0.8536684949080149
    },
    {
      "epoch": 40,
      "val": 0.8656494509220124
    },
    {
      "epoch": 50,
      "val": 0.8550735311508179
    },
    {
      "epoch": 60,
      "val": 0.8712779554684956
    },
    {
      "epoch": 70,
      "val": 0.8763506297747293
    },
    {
      "epoch": 80,
      "val": 0.8766111243724822
    },
    {
      "epoch": 90,
      "val": 0.8800485188961029
    },
    {
      "epoch": 100,
      "val": 0.876343323771159
    },
    {
      "epoch": 110,
      "val": 0.8834912961324056
    },
    {
      "epoch": 120,
      "val": 0.8836601014773051
    },
    {
      "epoch": 130,
      "val": 0.8839066813945772
    },
    {
      "epoch": 140,
      "val": 0.8846724081039428
    },
    {
      "epoch": 150,
      "val": 0.885894590139389
    },
    {
      "epoch": 160,
      "val": 0.8854919153849284
    },
    {
      "epoch": 170,
      "val": 0.8841688966115315
    },
    {
      "epoch": 180,
      "val": 0.8889011031468709
    },
    {
      "epoch": 190,
      "val": 0.8862967862447103
    },
    {
      "epoch": 200,
      "val": 0.8898394281069436
    },
    {
      "epoch": 210,
      "val": 0.8895475463390351
    },
    {
      "epoch": 220,
      "val": 0.8907114349683126
    },
    {
      "epoch": 230,
      "val": 0.8897309388955433
    },
    {
      "epoch": 240,
      "val": 0.8888036832332612
    },
    {
      "epoch": 250,
      "val": 0.8889256729920705
    },
    {
      "epoch": 260,
      "val": 0.8856952212174735
    },
    {
      "epoch": 270,
      "val": 0.8883878613789876
    },
    {
      "epoch": 280,
      "val": 0.8930893395582835
    },
    {
      "epoch": 290,
      "val": 0.892963383801778
    },
    {
      "epoch": 299,
      "val": 0.8926776920477549
    }
  ],
  "minutes": 656.8
}